machinevisiontoolbox/BagOfWords.py
machinevisiontoolbox/BundleAdjust.py
machinevisiontoolbox/Camera.py
machinevisiontoolbox/ImageBlobs.py
machinevisiontoolbox/ImageColor.py
machinevisiontoolbox/ImageConstants.py
machinevisiontoolbox/ImageCore.py
machinevisiontoolbox/ImageFiducials.py
machinevisiontoolbox/ImageIO.py
machinevisiontoolbox/ImageLineFeatures.py
machinevisiontoolbox/ImageMorph.py
machinevisiontoolbox/ImageMultiview.py
machinevisiontoolbox/ImagePointFeatures.py
machinevisiontoolbox/ImageProcessing.py
machinevisiontoolbox/ImageRegionFeatures.py
machinevisiontoolbox/ImageReshape.py
machinevisiontoolbox/ImageSpatial.py
machinevisiontoolbox/ImageWholeFeatures.py
machinevisiontoolbox/PointCloud.py
machinevisiontoolbox/Sources.py
machinevisiontoolbox/VisualServo.py
machinevisiontoolbox/__init__.py
machinevisiontoolbox/aruco0.pdf
machinevisiontoolbox/aruco50.pdf
machinevisiontoolbox/camera_derivatives.py
machinevisiontoolbox/decorators.py
machinevisiontoolbox/fiducial.py
machinevisiontoolbox/machinevision-toolbox-python.code-workspace
machinevisiontoolbox/mvtb_types.py
machinevisiontoolbox/newcameras.py
machinevisiontoolbox/base/__init__.py
machinevisiontoolbox/base/color.py
machinevisiontoolbox/base/data.py
machinevisiontoolbox/base/esttheta.py
machinevisiontoolbox/base/findpeaks.py
machinevisiontoolbox/base/graphics.py
machinevisiontoolbox/base/imageio.py
machinevisiontoolbox/base/meshgrid.py
machinevisiontoolbox/base/shapes.py
machinevisiontoolbox/base/types.py
machinevisiontoolbox/base/version.py
machinevisiontoolbox/bin/ce.py
machinevisiontoolbox/bin/imtool.py
machinevisiontoolbox/bin/mvtbtool.py
machinevisiontoolbox/bin/tagtool.py
machinevisiontoolbox/blocks/__init__.py
machinevisiontoolbox/blocks/camera.py
machinevisiontoolbox/blocks/test_blocks.py
machinevisiontoolbox/blocks/Icons/camera.png
machinevisiontoolbox/blocks/Icons/estpose_p.png
machinevisiontoolbox/blocks/Icons/icons.sh
machinevisiontoolbox/blocks/Icons/imageplane.png
machinevision_toolbox_python-1.0.3.dist-info/METADATA
machinevision_toolbox_python-1.0.3.dist-info/WHEEL
machinevision_toolbox_python-1.0.3.dist-info/entry_points.txt
machinevision_toolbox_python-1.0.3.dist-info/licenses/LICENSE
machinevision_toolbox_python-1.0.3.dist-info/RECORD
