Metadata-Version: 2.4
Name: machinevision-toolbox-python
Version: 1.0.3
Summary: Python tools for machine vision - education and research
Project-URL: Homepage, https://github.com/petercorke/machinevision-toolbox-python
Project-URL: Bug Tracker, https://github.com/pypa/sampleproject/issues
Project-URL: Documentation, https://petercorke.github.io/machinevision-toolbox-python
Project-URL: GitHub Source, https://github.com/petercorke/machinevision-toolbox-python
Project-URL: Changelog, https://github.com/petercorke/machinevision-toolbox-python/blob/master/CHANGELOG.md
Author: Dorian Tsai
Author-email: Peter Corke <rvc@petercorke.com>
License-File: LICENSE
Keywords: blobs,bundle adjustment,color,computer vision,image features,image segmentation,machine vision,morphology,multiview geometry,open3d,opencv,stereo vision,visual servoing
Classifier: Development Status :: 5 - Production/Stable
Classifier: Intended Audience :: Developers
Classifier: License :: OSI Approved :: MIT License
Classifier: Operating System :: OS Independent
Classifier: Programming Language :: Python :: 3.10
Classifier: Programming Language :: Python :: 3.11
Classifier: Programming Language :: Python :: 3.12
Requires-Python: >=3.10
Requires-Dist: ansitable
Requires-Dist: matplotlib
Requires-Dist: mvtb-data
Requires-Dist: numpy
Requires-Dist: opencv-contrib-python
Requires-Dist: opencv-python
Requires-Dist: pgraph-python
Requires-Dist: scipy
Requires-Dist: spatialmath-python
Provides-Extra: dev
Requires-Dist: coverage; extra == 'dev'
Requires-Dist: flake8; extra == 'dev'
Requires-Dist: pytest; extra == 'dev'
Provides-Extra: docs
Requires-Dist: recommonmark; extra == 'docs'
Requires-Dist: sphinx; extra == 'docs'
Requires-Dist: sphinx-autorun; extra == 'docs'
Requires-Dist: sphinx-favicon; extra == 'docs'
Requires-Dist: sphinx-markdown-tables; extra == 'docs'
Requires-Dist: sphinx-rtd-theme; extra == 'docs'
Requires-Dist: sphinxcontrib-jsmath; extra == 'docs'
Provides-Extra: jupyter
Requires-Dist: ipympl; extra == 'jupyter'
Requires-Dist: ipywidgets; extra == 'jupyter'
Provides-Extra: open3d
Requires-Dist: open3d-python; extra == 'open3d'
